LICENSE
README.rst
setup.py
PyLandslide/__init__.py
PyLandslide/cli.py
PyLandslide/data_preparation.py
PyLandslide/sensitivity.py
PyLandslide/weightrange.py
PyLandslide.egg-info/PKG-INFO
PyLandslide.egg-info/SOURCES.txt
PyLandslide.egg-info/dependency_links.txt
PyLandslide.egg-info/entry_points.txt
PyLandslide.egg-info/requires.txt
PyLandslide.egg-info/top_level.txt
tests/test_sensitivity.py
tests/test_weightrange.py